api_analytics/__init__.py
api_analytics/core.py
api_analytics/tornado.py
tornado_analytics-1.2.4.dist-info/LICENSE
tornado_analytics-1.2.4.dist-info/METADATA
tornado_analytics-1.2.4.dist-info/WHEEL
tornado_analytics-1.2.4.dist-info/top_level.txt
tornado_analytics-1.2.4.dist-info/RECORD
