Metadata-Version: 2.2
Name: tornado-analytics
Version: 1.2.4
Summary: Monitoring and analytics for Tornado applications.
Home-page: https://github.com/tom-draper/api-analytics
Author: Tom Draper
Author-email: Tom Draper <tomjdraper1@gmail.com>
License: MIT License
Project-URL: repository, https://github.com/tom-draper/api-analytics
Keywords: analytics,api,dashboard,tornado,middleware
Classifier: License :: OSI Approved :: MIT License
Classifier: Programming Language :: Python
Classifier: Programming Language :: Python :: 3
Requires-Python: >=3.6
License-File: LICENSE
Requires-Dist: tornado
Requires-Dist: requests
Provides-Extra: build
Requires-Dist: build; extra == "build"
Requires-Dist: twine; extra == "build"
Provides-Extra: dev
Requires-Dist: pytest; extra == "dev"
Dynamic: author
Dynamic: home-page
Dynamic: requires-python
